prismbot/__init__.py
prismbot-0.0.1.dist-info/METADATA
prismbot-0.0.1.dist-info/WHEEL
prismbot-0.0.1.dist-info/RECORD
